scvi/__init__.py
scvi/_constants.py
scvi/_settings.py
scvi/_types.py
scvi/autotune/__init__.py
scvi/autotune/_experiment.py
scvi/autotune/_tune.py
scvi/criticism/__init__.py
scvi/criticism/_constants.py
scvi/criticism/_create_criticism_report.py
scvi/criticism/_ppc.py
scvi/data/__init__.py
scvi/data/_anntorchdataset.py
scvi/data/_compat.py
scvi/data/_constants.py
scvi/data/_datasets.py
scvi/data/_download.py
scvi/data/_manager.py
scvi/data/_preprocessing.py
scvi/data/_read.py
scvi/data/_utils.py
scvi/data/_built_in_data/__init__.py
scvi/data/_built_in_data/_brain_large.py
scvi/data/_built_in_data/_cellxgene.py
scvi/data/_built_in_data/_cite_seq.py
scvi/data/_built_in_data/_cortex.py
scvi/data/_built_in_data/_csv.py
scvi/data/_built_in_data/_dataset_10x.py
scvi/data/_built_in_data/_heartcellatlas.py
scvi/data/_built_in_data/_loom.py
scvi/data/_built_in_data/_pbmc.py
scvi/data/_built_in_data/_smfish.py
scvi/data/_built_in_data/_synthetic.py
scvi/data/fields/__init__.py
scvi/data/fields/_arraylike_field.py
scvi/data/fields/_base_field.py
scvi/data/fields/_dataframe_field.py
scvi/data/fields/_layer_field.py
scvi/data/fields/_mudata.py
scvi/data/fields/_protein.py
scvi/data/fields/_scanvi.py
scvi/data/fields/_uns_field.py
scvi/dataloaders/__init__.py
scvi/dataloaders/_ann_dataloader.py
scvi/dataloaders/_anncollection.py
scvi/dataloaders/_concat_dataloader.py
scvi/dataloaders/_custom_dataloaders.py
scvi/dataloaders/_data_splitting.py
scvi/dataloaders/_samplers.py
scvi/dataloaders/_semi_dataloader.py
scvi/distributions/__init__.py
scvi/distributions/_beta_binomial.py
scvi/distributions/_constraints.py
scvi/distributions/_negative_binomial.py
scvi/distributions/_normal.py
scvi/distributions/_utils.py
scvi/external/__init__.py
scvi/external/cellassign/__init__.py
scvi/external/cellassign/_model.py
scvi/external/cellassign/_module.py
scvi/external/contrastivevi/__init__.py
scvi/external/contrastivevi/_contrastive_data_splitting.py
scvi_tools-1.4.0.post1.dist-info/METADATA
scvi_tools-1.4.0.post1.dist-info/WHEEL
scvi_tools-1.4.0.post1.dist-info/licenses/LICENSE
scvi_tools-1.4.0.post1.dist-info/RECORD
